[
 {
  "SchoolYear": "2021-2022",
  "Sector": "District",
  "SubSector": "District",
  "ULCSCode": "2680",
  "SchoolName": "The Science Leadership Academy at Beeber",
  "LearningNetwork": "Innovation",
  "GradeLevel": "05",
  "StudentEnrollment": "31",
  "ELCount": "1",
  "ELPCT": "3.23",
  "NotELCount": "30",
  "NotELPCT": "96.77",
  "IEPCount": "2",
  "IEPPCT": "6.45",
  "NotIEPCount": "29",
  "NotIEPPCT": "93.55",
  "FemaleCount": "15",
  "FemalePCT": "48.39",
  "MaleCount": "16",
  "MalePCT": "51.61",
  "AmericanIndianCount": "0",
  "AmericanIndianPCT": "0.00",
  "AsianCount": "2",
  "AsianPCT": "6.45",
  "BlackAfricanAmericanCount": "17",
  "BlackAfricanAmericanPCT": "54.84",
  "HispanicCount": "0",
  "HispanicPCT": "0.00",
  "MultiRaceCount": "3",
  "MultiRacePCT": "9.68",
  "PacificIslanderCount": "0",
  "PacificIslanderPCT": "0.00",
  "WhiteCount": "9",
  "WhitePCT": "29.03",
  "CEPEconomicallyDisadvantagedRate": ""
 },
 {
  "SchoolYear": "2021-2022",
  "Sector": "District",
  "SubSector": "District",
  "ULCSCode": "2680",
  "SchoolName": "The Science Leadership Academy at Beeber",
  "LearningNetwork": "Innovation",
  "GradeLevel": "06",
  "StudentEnrollment": "57",
  "ELCount": "1",
  "ELPCT": "1.75",
  "NotELCount": "56",
  "NotELPCT": "98.25",
  "IEPCount": "3",
  "IEPPCT": "5.26",
  "NotIEPCount": "54",
  "NotIEPPCT": "94.74",
  "FemaleCount": "33",
  "FemalePCT": "57.89",
  "MaleCount": "24",
  "MalePCT": "42.11",
  "AmericanIndianCount": "0",
  "AmericanIndianPCT": "0.00",
  "AsianCount": "2",
  "AsianPCT": "3.51",
  "BlackAfricanAmericanCount": "44",
  "BlackAfricanAmericanPCT": "77.19",
  "HispanicCount": "2",
  "HispanicPCT": "3.51",
  "MultiRaceCount": "1",
  "MultiRacePCT": "1.75",
  "PacificIslanderCount": "0",
  "PacificIslanderPCT": "0.00",
  "WhiteCount": "8",
  "WhitePCT": "14.04",
  "CEPEconomicallyDisadvantagedRate": ""
 },
 {
  "SchoolYear": "2021-2022",
  "Sector": "District",
  "SubSector": "District",
  "ULCSCode": "2680",
  "SchoolName": "The Science Leadership Academy at Beeber",
  "LearningNetwork": "Innovation",
  "GradeLevel": "07",
  "StudentEnrollment": "64",
  "ELCount": "0",
  "ELPCT": "0.00",
  "NotELCount": "64",
  "NotELPCT": "100.00",
  "IEPCount": "2",
  "IEPPCT": "3.13",
  "NotIEPCount": "62",
  "NotIEPPCT": "96.88",
  "FemaleCount": "36",
  "FemalePCT": "56.25",
  "MaleCount": "28",
  "MalePCT": "43.75",
  "AmericanIndianCount": "0",
  "AmericanIndianPCT": "0.00",
  "AsianCount": "4",
  "AsianPCT": "6.25",
  "BlackAfricanAmericanCount": "51",
  "BlackAfricanAmericanPCT": "79.69",
  "HispanicCount": "3",
  "HispanicPCT": "4.69",
  "MultiRaceCount": "0",
  "MultiRacePCT": "0.00",
  "PacificIslanderCount": "0",
  "PacificIslanderPCT": "0.00",
  "WhiteCount": "6",
  "WhitePCT": "9.38",
  "CEPEconomicallyDisadvantagedRate": ""
 },
 {
  "SchoolYear": "2021-2022",
  "Sector": "District",
  "SubSector": "District",
  "ULCSCode": "2680",
  "SchoolName": "The Science Leadership Academy at Beeber",
  "LearningNetwork": "Innovation",
  "GradeLevel": "08",
  "StudentEnrollment": "60",
  "ELCount": "0",
  "ELPCT": "0.00",
  "NotELCount": "60",
  "NotELPCT": "100.00",
  "IEPCount": "2",
  "IEPPCT": "3.33",
  "NotIEPCount": "58",
  "NotIEPPCT": "96.67",
  "FemaleCount": "35",
  "FemalePCT": "58.33",
  "MaleCount": "25",
  "MalePCT": "41.67",
  "AmericanIndianCount": "0",
  "AmericanIndianPCT": "0.00",
  "AsianCount": "0",
  "AsianPCT": "0.00",
  "BlackAfricanAmericanCount": "50",
  "BlackAfricanAmericanPCT": "83.33",
  "HispanicCount": "0",
  "HispanicPCT": "0.00",
  "MultiRaceCount": "3",
  "MultiRacePCT": "5.00",
  "PacificIslanderCount": "0",
  "PacificIslanderPCT": "0.00",
  "WhiteCount": "7",
  "WhitePCT": "11.67",
  "CEPEconomicallyDisadvantagedRate": ""
 },
 {
  "SchoolYear": "2021-2022",
  "Sector": "District",
  "SubSector": "District",
  "ULCSCode": "2680",
  "SchoolName": "The Science Leadership Academy at Beeber",
  "LearningNetwork": "Innovation",
  "GradeLevel": "09",
  "StudentEnrollment": "117",
  "ELCount": "7",
  "ELPCT": "5.98",
  "NotELCount": "110",
  "NotELPCT": "94.02",
  "IEPCount": "12",
  "IEPPCT": "10.26",
  "NotIEPCount": "105",
  "NotIEPPCT": "89.74",
  "FemaleCount": "58",
  "FemalePCT": "49.57",
  "MaleCount": "59",
  "MalePCT": "50.43",
  "AmericanIndianCount": "0",
  "AmericanIndianPCT": "0.00",
  "AsianCount": "9",
  "AsianPCT": "7.69",
  "BlackAfricanAmericanCount": "72",
  "BlackAfricanAmericanPCT": "61.54",
  "HispanicCount": "9",
  "HispanicPCT": "7.69",
  "MultiRaceCount": "9",
  "MultiRacePCT": "7.69",
  "PacificIslanderCount": "0",
  "PacificIslanderPCT": "0.00",
  "WhiteCount": "18",
  "WhitePCT": "15.38",
  "CEPEconomicallyDisadvantagedRate": ""
 },
 {
  "SchoolYear": "2021-2022",
  "Sector": "District",
  "SubSector": "District",
  "ULCSCode": "2680",
  "SchoolName": "The Science Leadership Academy at Beeber",
  "LearningNetwork": "Innovation",
  "GradeLevel": "10",
  "StudentEnrollment": "123",
  "ELCount": "4",
  "ELPCT": "3.25",
  "NotELCount": "119",
  "NotELPCT": "96.75",
  "IEPCount": "8",
  "IEPPCT": "6.50",
  "NotIEPCount": "115",
  "NotIEPPCT": "93.50",
  "FemaleCount": "62",
  "FemalePCT": "50.41",
  "MaleCount": "61",
  "MalePCT": "49.59",
  "AmericanIndianCount": "1",
  "AmericanIndianPCT": "0.81",
  "AsianCount": "5",
  "AsianPCT": "4.07",
  "BlackAfricanAmericanCount": "90",
  "BlackAfricanAmericanPCT": "73.17",
  "HispanicCount": "8",
  "HispanicPCT": "6.50",
  "MultiRaceCount": "4",
  "MultiRacePCT": "3.25",
  "PacificIslanderCount": "0",
  "PacificIslanderPCT": "0.00",
  "WhiteCount": "15",
  "WhitePCT": "12.20",
  "CEPEconomicallyDisadvantagedRate": ""
 },
 {
  "SchoolYear": "2021-2022",
  "Sector": "District",
  "SubSector": "District",
  "ULCSCode": "2680",
  "SchoolName": "The Science Leadership Academy at Beeber",
  "LearningNetwork": "Innovation",
  "GradeLevel": "11",
  "StudentEnrollment": "114",
  "ELCount": "9",
  "ELPCT": "7.89",
  "NotELCount": "105",
  "NotELPCT": "92.11",
  "IEPCount": "9",
  "IEPPCT": "7.89",
  "NotIEPCount": "105",
  "NotIEPPCT": "92.11",
  "FemaleCount": "64",
  "FemalePCT": "56.14",
  "MaleCount": "50",
  "MalePCT": "43.86",
  "AmericanIndianCount": "0",
  "AmericanIndianPCT": "0.00",
  "AsianCount": "4",
  "AsianPCT": "3.51",
  "BlackAfricanAmericanCount": "90",
  "BlackAfricanAmericanPCT": "78.95",
  "HispanicCount": "12",
  "HispanicPCT": "10.53",
  "MultiRaceCount": "3",
  "MultiRacePCT": "2.63",
  "PacificIslanderCount": "0",
  "PacificIslanderPCT": "0.00",
  "WhiteCount": "5",
  "WhitePCT": "4.39",
  "CEPEconomicallyDisadvantagedRate": ""
 },
 {
  "SchoolYear": "2021-2022",
  "Sector": "District",
  "SubSector": "District",
  "ULCSCode": "2680",
  "SchoolName": "The Science Leadership Academy at Beeber",
  "LearningNetwork": "Innovation",
  "GradeLevel": "12",
  "StudentEnrollment": "111",
  "ELCount": "7",
  "ELPCT": "6.31",
  "NotELCount": "104",
  "NotELPCT": "93.69",
  "IEPCount": "6",
  "IEPPCT": "5.41",
  "NotIEPCount": "105",
  "NotIEPPCT": "94.59",
  "FemaleCount": "55",
  "FemalePCT": "49.55",
  "MaleCount": "56",
  "MalePCT": "50.45",
  "AmericanIndianCount": "0",
  "AmericanIndianPCT": "0.00",
  "AsianCount": "7",
  "AsianPCT": "6.31",
  "BlackAfricanAmericanCount": "76",
  "BlackAfricanAmericanPCT": "68.47",
  "HispanicCount": "4",
  "HispanicPCT": "3.60",
  "MultiRaceCount": "5",
  "MultiRacePCT": "4.50",
  "PacificIslanderCount": "0",
  "PacificIslanderPCT": "0.00",
  "WhiteCount": "19",
  "WhitePCT": "17.12",
  "CEPEconomicallyDisadvantagedRate": ""
 },
 {
  "SchoolYear": "2021-2022",
  "Sector": "District",
  "SubSector": "District",
  "ULCSCode": "2680",
  "SchoolName": "The Science Leadership Academy at Beeber",
  "LearningNetwork": "Innovation",
  "GradeLevel": "All Grades",
  "StudentEnrollment": "677",
  "ELCount": "29",
  "ELPCT": "4.28",
  "NotELCount": "648",
  "NotELPCT": "95.72",
  "IEPCount": "44",
  "IEPPCT": "6.50",
  "NotIEPCount": "633",
  "NotIEPPCT": "93.50",
  "FemaleCount": "358",
  "FemalePCT": "52.88",
  "MaleCount": "319",
  "MalePCT": "47.12",
  "AmericanIndianCount": "1",
  "AmericanIndianPCT": "0.15",
  "AsianCount": "33",
  "AsianPCT": "4.87",
  "BlackAfricanAmericanCount": "490",
  "BlackAfricanAmericanPCT": "72.38",
  "HispanicCount": "38",
  "HispanicPCT": "5.61",
  "MultiRaceCount": "28",
  "MultiRacePCT": "4.14",
  "PacificIslanderCount": "0",
  "PacificIslanderPCT": "0.00",
  "WhiteCount": "87",
  "WhitePCT": "12.85",
  "CEPEconomicallyDisadvantagedRate": "74.92"
 }
]