[
 {
  "SchoolYear": "2021-2022",
  "Sector": "Charter",
  "SubSector": "Phila Charters",
  "ULCSCode": "3322",
  "SchoolName": "Philadelphia Academy Charter School",
  "LearningNetwork": "Charters",
  "GradeLevel": "00",
  "StudentEnrollment": "58",
  "ELCount": "",
  "ELPCT": "",
  "NotELCount": "",
  "NotELPCT": "",
  "IEPCount": "7",
  "IEPPCT": "12.07",
  "NotIEPCount": "51",
  "NotIEPPCT": "87.93",
  "FemaleCount": "33",
  "FemalePCT": "56.90",
  "MaleCount": "25",
  "MalePCT": "43.10",
  "AmericanIndianCount": "1",
  "AmericanIndianPCT": "1.72",
  "AsianCount": "8",
  "AsianPCT": "13.79",
  "BlackAfricanAmericanCount": "2",
  "BlackAfricanAmericanPCT": "3.45",
  "HispanicCount": "11",
  "HispanicPCT": "18.97",
  "MultiRaceCount": "5",
  "MultiRacePCT": "8.62",
  "PacificIslanderCount": "0",
  "PacificIslanderPCT": "0.00",
  "WhiteCount": "31",
  "WhitePCT": "53.45",
  "CEPEconomicallyDisadvantagedRate": ""
 },
 {
  "SchoolYear": "2021-2022",
  "Sector": "Charter",
  "SubSector": "Phila Charters",
  "ULCSCode": "3322",
  "SchoolName": "Philadelphia Academy Charter School",
  "LearningNetwork": "Charters",
  "GradeLevel": "01",
  "StudentEnrollment": "65",
  "ELCount": "",
  "ELPCT": "",
  "NotELCount": "",
  "NotELPCT": "",
  "IEPCount": "7",
  "IEPPCT": "10.77",
  "NotIEPCount": "58",
  "NotIEPPCT": "89.23",
  "FemaleCount": "34",
  "FemalePCT": "52.31",
  "MaleCount": "31",
  "MalePCT": "47.69",
  "AmericanIndianCount": "0",
  "AmericanIndianPCT": "0.00",
  "AsianCount": "2",
  "AsianPCT": "3.08",
  "BlackAfricanAmericanCount": "6",
  "BlackAfricanAmericanPCT": "9.23",
  "HispanicCount": "4",
  "HispanicPCT": "6.15",
  "MultiRaceCount": "14",
  "MultiRacePCT": "21.54",
  "PacificIslanderCount": "1",
  "PacificIslanderPCT": "1.54",
  "WhiteCount": "38",
  "WhitePCT": "58.46",
  "CEPEconomicallyDisadvantagedRate": ""
 },
 {
  "SchoolYear": "2021-2022",
  "Sector": "Charter",
  "SubSector": "Phila Charters",
  "ULCSCode": "3322",
  "SchoolName": "Philadelphia Academy Charter School",
  "LearningNetwork": "Charters",
  "GradeLevel": "02",
  "StudentEnrollment": "62",
  "ELCount": "",
  "ELPCT": "",
  "NotELCount": "",
  "NotELPCT": "",
  "IEPCount": "14",
  "IEPPCT": "22.58",
  "NotIEPCount": "48",
  "NotIEPPCT": "77.42",
  "FemaleCount": "25",
  "FemalePCT": "40.32",
  "MaleCount": "37",
  "MalePCT": "59.68",
  "AmericanIndianCount": "0",
  "AmericanIndianPCT": "0.00",
  "AsianCount": "1",
  "AsianPCT": "1.61",
  "BlackAfricanAmericanCount": "7",
  "BlackAfricanAmericanPCT": "11.29",
  "HispanicCount": "7",
  "HispanicPCT": "11.29",
  "MultiRaceCount": "4",
  "MultiRacePCT": "6.45",
  "PacificIslanderCount": "0",
  "PacificIslanderPCT": "0.00",
  "WhiteCount": "43",
  "WhitePCT": "69.35",
  "CEPEconomicallyDisadvantagedRate": ""
 },
 {
  "SchoolYear": "2021-2022",
  "Sector": "Charter",
  "SubSector": "Phila Charters",
  "ULCSCode": "3322",
  "SchoolName": "Philadelphia Academy Charter School",
  "LearningNetwork": "Charters",
  "GradeLevel": "03",
  "StudentEnrollment": "65",
  "ELCount": "",
  "ELPCT": "",
  "NotELCount": "",
  "NotELPCT": "",
  "IEPCount": "12",
  "IEPPCT": "18.46",
  "NotIEPCount": "53",
  "NotIEPPCT": "81.54",
  "FemaleCount": "37",
  "FemalePCT": "56.92",
  "MaleCount": "28",
  "MalePCT": "43.08",
  "AmericanIndianCount": "0",
  "AmericanIndianPCT": "0.00",
  "AsianCount": "8",
  "AsianPCT": "12.31",
  "BlackAfricanAmericanCount": "9",
  "BlackAfricanAmericanPCT": "13.85",
  "HispanicCount": "5",
  "HispanicPCT": "7.69",
  "MultiRaceCount": "2",
  "MultiRacePCT": "3.08",
  "PacificIslanderCount": "0",
  "PacificIslanderPCT": "0.00",
  "WhiteCount": "41",
  "WhitePCT": "63.08",
  "CEPEconomicallyDisadvantagedRate": ""
 },
 {
  "SchoolYear": "2021-2022",
  "Sector": "Charter",
  "SubSector": "Phila Charters",
  "ULCSCode": "3322",
  "SchoolName": "Philadelphia Academy Charter School",
  "LearningNetwork": "Charters",
  "GradeLevel": "04",
  "StudentEnrollment": "83",
  "ELCount": "",
  "ELPCT": "",
  "NotELCount": "",
  "NotELPCT": "",
  "IEPCount": "10",
  "IEPPCT": "12.05",
  "NotIEPCount": "73",
  "NotIEPPCT": "87.95",
  "FemaleCount": "46",
  "FemalePCT": "55.42",
  "MaleCount": "37",
  "MalePCT": "44.58",
  "AmericanIndianCount": "0",
  "AmericanIndianPCT": "0.00",
  "AsianCount": "5",
  "AsianPCT": "6.02",
  "BlackAfricanAmericanCount": "7",
  "BlackAfricanAmericanPCT": "8.43",
  "HispanicCount": "12",
  "HispanicPCT": "14.46",
  "MultiRaceCount": "1",
  "MultiRacePCT": "1.20",
  "PacificIslanderCount": "0",
  "PacificIslanderPCT": "0.00",
  "WhiteCount": "58",
  "WhitePCT": "69.88",
  "CEPEconomicallyDisadvantagedRate": ""
 },
 {
  "SchoolYear": "2021-2022",
  "Sector": "Charter",
  "SubSector": "Phila Charters",
  "ULCSCode": "3322",
  "SchoolName": "Philadelphia Academy Charter School",
  "LearningNetwork": "Charters",
  "GradeLevel": "05",
  "StudentEnrollment": "83",
  "ELCount": "",
  "ELPCT": "",
  "NotELCount": "",
  "NotELPCT": "",
  "IEPCount": "14",
  "IEPPCT": "16.87",
  "NotIEPCount": "69",
  "NotIEPPCT": "83.13",
  "FemaleCount": "45",
  "FemalePCT": "54.22",
  "MaleCount": "38",
  "MalePCT": "45.78",
  "AmericanIndianCount": "1",
  "AmericanIndianPCT": "1.20",
  "AsianCount": "8",
  "AsianPCT": "9.64",
  "BlackAfricanAmericanCount": "4",
  "BlackAfricanAmericanPCT": "4.82",
  "HispanicCount": "7",
  "HispanicPCT": "8.43",
  "MultiRaceCount": "3",
  "MultiRacePCT": "3.61",
  "PacificIslanderCount": "0",
  "PacificIslanderPCT": "0.00",
  "WhiteCount": "60",
  "WhitePCT": "72.29",
  "CEPEconomicallyDisadvantagedRate": ""
 },
 {
  "SchoolYear": "2021-2022",
  "Sector": "Charter",
  "SubSector": "Phila Charters",
  "ULCSCode": "3322",
  "SchoolName": "Philadelphia Academy Charter School",
  "LearningNetwork": "Charters",
  "GradeLevel": "06",
  "StudentEnrollment": "84",
  "ELCount": "",
  "ELPCT": "",
  "NotELCount": "",
  "NotELPCT": "",
  "IEPCount": "16",
  "IEPPCT": "19.05",
  "NotIEPCount": "68",
  "NotIEPPCT": "80.95",
  "FemaleCount": "36",
  "FemalePCT": "42.86",
  "MaleCount": "48",
  "MalePCT": "57.14",
  "AmericanIndianCount": "0",
  "AmericanIndianPCT": "0.00",
  "AsianCount": "4",
  "AsianPCT": "4.76",
  "BlackAfricanAmericanCount": "9",
  "BlackAfricanAmericanPCT": "10.71",
  "HispanicCount": "9",
  "HispanicPCT": "10.71",
  "MultiRaceCount": "3",
  "MultiRacePCT": "3.57",
  "PacificIslanderCount": "1",
  "PacificIslanderPCT": "1.19",
  "WhiteCount": "58",
  "WhitePCT": "69.05",
  "CEPEconomicallyDisadvantagedRate": ""
 },
 {
  "SchoolYear": "2021-2022",
  "Sector": "Charter",
  "SubSector": "Phila Charters",
  "ULCSCode": "3322",
  "SchoolName": "Philadelphia Academy Charter School",
  "LearningNetwork": "Charters",
  "GradeLevel": "07",
  "StudentEnrollment": "82",
  "ELCount": "",
  "ELPCT": "",
  "NotELCount": "",
  "NotELPCT": "",
  "IEPCount": "13",
  "IEPPCT": "15.85",
  "NotIEPCount": "69",
  "NotIEPPCT": "84.15",
  "FemaleCount": "41",
  "FemalePCT": "50.00",
  "MaleCount": "41",
  "MalePCT": "50.00",
  "AmericanIndianCount": "0",
  "AmericanIndianPCT": "0.00",
  "AsianCount": "2",
  "AsianPCT": "2.44",
  "BlackAfricanAmericanCount": "5",
  "BlackAfricanAmericanPCT": "6.10",
  "HispanicCount": "5",
  "HispanicPCT": "6.10",
  "MultiRaceCount": "5",
  "MultiRacePCT": "6.10",
  "PacificIslanderCount": "0",
  "PacificIslanderPCT": "0.00",
  "WhiteCount": "65",
  "WhitePCT": "79.27",
  "CEPEconomicallyDisadvantagedRate": ""
 },
 {
  "SchoolYear": "2021-2022",
  "Sector": "Charter",
  "SubSector": "Phila Charters",
  "ULCSCode": "3322",
  "SchoolName": "Philadelphia Academy Charter School",
  "LearningNetwork": "Charters",
  "GradeLevel": "08",
  "StudentEnrollment": "83",
  "ELCount": "",
  "ELPCT": "",
  "NotELCount": "",
  "NotELPCT": "",
  "IEPCount": "14",
  "IEPPCT": "16.87",
  "NotIEPCount": "69",
  "NotIEPPCT": "83.13",
  "FemaleCount": "45",
  "FemalePCT": "54.22",
  "MaleCount": "38",
  "MalePCT": "45.78",
  "AmericanIndianCount": "0",
  "AmericanIndianPCT": "0.00",
  "AsianCount": "2",
  "AsianPCT": "2.41",
  "BlackAfricanAmericanCount": "4",
  "BlackAfricanAmericanPCT": "4.82",
  "HispanicCount": "6",
  "HispanicPCT": "7.23",
  "MultiRaceCount": "4",
  "MultiRacePCT": "4.82",
  "PacificIslanderCount": "0",
  "PacificIslanderPCT": "0.00",
  "WhiteCount": "67",
  "WhitePCT": "80.72",
  "CEPEconomicallyDisadvantagedRate": ""
 },
 {
  "SchoolYear": "2021-2022",
  "Sector": "Charter",
  "SubSector": "Phila Charters",
  "ULCSCode": "3322",
  "SchoolName": "Philadelphia Academy Charter School",
  "LearningNetwork": "Charters",
  "GradeLevel": "09",
  "StudentEnrollment": "122",
  "ELCount": "",
  "ELPCT": "",
  "NotELCount": "",
  "NotELPCT": "",
  "IEPCount": "17",
  "IEPPCT": "13.93",
  "NotIEPCount": "105",
  "NotIEPPCT": "86.07",
  "FemaleCount": "65",
  "FemalePCT": "53.28",
  "MaleCount": "57",
  "MalePCT": "46.72",
  "AmericanIndianCount": "1",
  "AmericanIndianPCT": "0.82",
  "AsianCount": "10",
  "AsianPCT": "8.20",
  "BlackAfricanAmericanCount": "23",
  "BlackAfricanAmericanPCT": "18.85",
  "HispanicCount": "20",
  "HispanicPCT": "16.39",
  "MultiRaceCount": "4",
  "MultiRacePCT": "3.28",
  "PacificIslanderCount": "1",
  "PacificIslanderPCT": "0.82",
  "WhiteCount": "63",
  "WhitePCT": "51.64",
  "CEPEconomicallyDisadvantagedRate": ""
 },
 {
  "SchoolYear": "2021-2022",
  "Sector": "Charter",
  "SubSector": "Phila Charters",
  "ULCSCode": "3322",
  "SchoolName": "Philadelphia Academy Charter School",
  "LearningNetwork": "Charters",
  "GradeLevel": "10",
  "StudentEnrollment": "114",
  "ELCount": "",
  "ELPCT": "",
  "NotELCount": "",
  "NotELPCT": "",
  "IEPCount": "27",
  "IEPPCT": "23.68",
  "NotIEPCount": "87",
  "NotIEPPCT": "76.32",
  "FemaleCount": "56",
  "FemalePCT": "49.12",
  "MaleCount": "58",
  "MalePCT": "50.88",
  "AmericanIndianCount": "0",
  "AmericanIndianPCT": "0.00",
  "AsianCount": "4",
  "AsianPCT": "3.51",
  "BlackAfricanAmericanCount": "21",
  "BlackAfricanAmericanPCT": "18.42",
  "HispanicCount": "8",
  "HispanicPCT": "7.02",
  "MultiRaceCount": "11",
  "MultiRacePCT": "9.65",
  "PacificIslanderCount": "0",
  "PacificIslanderPCT": "0.00",
  "WhiteCount": "70",
  "WhitePCT": "61.40",
  "CEPEconomicallyDisadvantagedRate": ""
 },
 {
  "SchoolYear": "2021-2022",
  "Sector": "Charter",
  "SubSector": "Phila Charters",
  "ULCSCode": "3322",
  "SchoolName": "Philadelphia Academy Charter School",
  "LearningNetwork": "Charters",
  "GradeLevel": "11",
  "StudentEnrollment": "102",
  "ELCount": "",
  "ELPCT": "",
  "NotELCount": "",
  "NotELPCT": "",
  "IEPCount": "22",
  "IEPPCT": "21.57",
  "NotIEPCount": "80",
  "NotIEPPCT": "78.43",
  "FemaleCount": "46",
  "FemalePCT": "45.10",
  "MaleCount": "56",
  "MalePCT": "54.90",
  "AmericanIndianCount": "1",
  "AmericanIndianPCT": "0.98",
  "AsianCount": "4",
  "AsianPCT": "3.92",
  "BlackAfricanAmericanCount": "15",
  "BlackAfricanAmericanPCT": "14.71",
  "HispanicCount": "7",
  "HispanicPCT": "6.86",
  "MultiRaceCount": "8",
  "MultiRacePCT": "7.84",
  "PacificIslanderCount": "0",
  "PacificIslanderPCT": "0.00",
  "WhiteCount": "67",
  "WhitePCT": "65.69",
  "CEPEconomicallyDisadvantagedRate": ""
 },
 {
  "SchoolYear": "2021-2022",
  "Sector": "Charter",
  "SubSector": "Phila Charters",
  "ULCSCode": "3322",
  "SchoolName": "Philadelphia Academy Charter School",
  "LearningNetwork": "Charters",
  "GradeLevel": "12",
  "StudentEnrollment": "107",
  "ELCount": "",
  "ELPCT": "",
  "NotELCount": "",
  "NotELPCT": "",
  "IEPCount": "34",
  "IEPPCT": "31.78",
  "NotIEPCount": "73",
  "NotIEPPCT": "68.22",
  "FemaleCount": "43",
  "FemalePCT": "40.19",
  "MaleCount": "64",
  "MalePCT": "59.81",
  "AmericanIndianCount": "0",
  "AmericanIndianPCT": "0.00",
  "AsianCount": "7",
  "AsianPCT": "6.54",
  "BlackAfricanAmericanCount": "14",
  "BlackAfricanAmericanPCT": "13.08",
  "HispanicCount": "8",
  "HispanicPCT": "7.48",
  "MultiRaceCount": "9",
  "MultiRacePCT": "8.41",
  "PacificIslanderCount": "0",
  "PacificIslanderPCT": "0.00",
  "WhiteCount": "69",
  "WhitePCT": "64.49",
  "CEPEconomicallyDisadvantagedRate": ""
 },
 {
  "SchoolYear": "2021-2022",
  "Sector": "Charter",
  "SubSector": "Phila Charters",
  "ULCSCode": "3322",
  "SchoolName": "Philadelphia Academy Charter School",
  "LearningNetwork": "Charters",
  "GradeLevel": "All Grades",
  "StudentEnrollment": "1110",
  "ELCount": "",
  "ELPCT": "",
  "NotELCount": "",
  "NotELPCT": "",
  "IEPCount": "207",
  "IEPPCT": "18.65",
  "NotIEPCount": "903",
  "NotIEPPCT": "81.35",
  "FemaleCount": "552",
  "FemalePCT": "49.73",
  "MaleCount": "558",
  "MalePCT": "50.27",
  "AmericanIndianCount": "4",
  "AmericanIndianPCT": "0.36",
  "AsianCount": "65",
  "AsianPCT": "5.86",
  "BlackAfricanAmericanCount": "126",
  "BlackAfricanAmericanPCT": "11.35",
  "HispanicCount": "109",
  "HispanicPCT": "9.82",
  "MultiRaceCount": "73",
  "MultiRacePCT": "6.58",
  "PacificIslanderCount": "3",
  "PacificIslanderPCT": "0.27",
  "WhiteCount": "730",
  "WhitePCT": "65.77",
  "CEPEconomicallyDisadvantagedRate": ""
 }
]