[
 {
  "SchoolYear": "2021-2022",
  "Sector": "District",
  "SubSector": "District",
  "ULCSCode": "4560",
  "SchoolName": "William D. Kelley School",
  "LearningNetwork": "Network 11",
  "GradeLevel": "00",
  "StudentEnrollment": "28",
  "ELCount": "0",
  "ELPCT": "0.00",
  "NotELCount": "28",
  "NotELPCT": "100.00",
  "IEPCount": "1",
  "IEPPCT": "3.57",
  "NotIEPCount": "27",
  "NotIEPPCT": "96.43",
  "FemaleCount": "15",
  "FemalePCT": "53.57",
  "MaleCount": "13",
  "MalePCT": "46.43",
  "AmericanIndianCount": "0",
  "AmericanIndianPCT": "0.00",
  "AsianCount": "0",
  "AsianPCT": "0.00",
  "BlackAfricanAmericanCount": "25",
  "BlackAfricanAmericanPCT": "89.29",
  "HispanicCount": "3",
  "HispanicPCT": "10.71",
  "MultiRaceCount": "0",
  "MultiRacePCT": "0.00",
  "PacificIslanderCount": "0",
  "PacificIslanderPCT": "0.00",
  "WhiteCount": "0",
  "WhitePCT": "0.00",
  "CEPEconomicallyDisadvantagedRate": ""
 },
 {
  "SchoolYear": "2021-2022",
  "Sector": "District",
  "SubSector": "District",
  "ULCSCode": "4560",
  "SchoolName": "William D. Kelley School",
  "LearningNetwork": "Network 11",
  "GradeLevel": "01",
  "StudentEnrollment": "26",
  "ELCount": "0",
  "ELPCT": "0.00",
  "NotELCount": "26",
  "NotELPCT": "100.00",
  "IEPCount": "1",
  "IEPPCT": "3.85",
  "NotIEPCount": "25",
  "NotIEPPCT": "96.15",
  "FemaleCount": "10",
  "FemalePCT": "38.46",
  "MaleCount": "16",
  "MalePCT": "61.54",
  "AmericanIndianCount": "1",
  "AmericanIndianPCT": "3.85",
  "AsianCount": "0",
  "AsianPCT": "0.00",
  "BlackAfricanAmericanCount": "23",
  "BlackAfricanAmericanPCT": "88.46",
  "HispanicCount": "2",
  "HispanicPCT": "7.69",
  "MultiRaceCount": "0",
  "MultiRacePCT": "0.00",
  "PacificIslanderCount": "0",
  "PacificIslanderPCT": "0.00",
  "WhiteCount": "0",
  "WhitePCT": "0.00",
  "CEPEconomicallyDisadvantagedRate": ""
 },
 {
  "SchoolYear": "2021-2022",
  "Sector": "District",
  "SubSector": "District",
  "ULCSCode": "4560",
  "SchoolName": "William D. Kelley School",
  "LearningNetwork": "Network 11",
  "GradeLevel": "02",
  "StudentEnrollment": "19",
  "ELCount": "0",
  "ELPCT": "0.00",
  "NotELCount": "19",
  "NotELPCT": "100.00",
  "IEPCount": "2",
  "IEPPCT": "10.53",
  "NotIEPCount": "17",
  "NotIEPPCT": "89.47",
  "FemaleCount": "5",
  "FemalePCT": "26.32",
  "MaleCount": "14",
  "MalePCT": "73.68",
  "AmericanIndianCount": "0",
  "AmericanIndianPCT": "0.00",
  "AsianCount": "0",
  "AsianPCT": "0.00",
  "BlackAfricanAmericanCount": "18",
  "BlackAfricanAmericanPCT": "94.74",
  "HispanicCount": "1",
  "HispanicPCT": "5.26",
  "MultiRaceCount": "0",
  "MultiRacePCT": "0.00",
  "PacificIslanderCount": "0",
  "PacificIslanderPCT": "0.00",
  "WhiteCount": "0",
  "WhitePCT": "0.00",
  "CEPEconomicallyDisadvantagedRate": ""
 },
 {
  "SchoolYear": "2021-2022",
  "Sector": "District",
  "SubSector": "District",
  "ULCSCode": "4560",
  "SchoolName": "William D. Kelley School",
  "LearningNetwork": "Network 11",
  "GradeLevel": "03",
  "StudentEnrollment": "44",
  "ELCount": "0",
  "ELPCT": "0.00",
  "NotELCount": "44",
  "NotELPCT": "100.00",
  "IEPCount": "8",
  "IEPPCT": "18.18",
  "NotIEPCount": "36",
  "NotIEPPCT": "81.82",
  "FemaleCount": "19",
  "FemalePCT": "43.18",
  "MaleCount": "25",
  "MalePCT": "56.82",
  "AmericanIndianCount": "0",
  "AmericanIndianPCT": "0.00",
  "AsianCount": "0",
  "AsianPCT": "0.00",
  "BlackAfricanAmericanCount": "44",
  "BlackAfricanAmericanPCT": "100.00",
  "HispanicCount": "0",
  "HispanicPCT": "0.00",
  "MultiRaceCount": "0",
  "MultiRacePCT": "0.00",
  "PacificIslanderCount": "0",
  "PacificIslanderPCT": "0.00",
  "WhiteCount": "0",
  "WhitePCT": "0.00",
  "CEPEconomicallyDisadvantagedRate": ""
 },
 {
  "SchoolYear": "2021-2022",
  "Sector": "District",
  "SubSector": "District",
  "ULCSCode": "4560",
  "SchoolName": "William D. Kelley School",
  "LearningNetwork": "Network 11",
  "GradeLevel": "04",
  "StudentEnrollment": "24",
  "ELCount": "0",
  "ELPCT": "0.00",
  "NotELCount": "24",
  "NotELPCT": "100.00",
  "IEPCount": "6",
  "IEPPCT": "25.00",
  "NotIEPCount": "18",
  "NotIEPPCT": "75.00",
  "FemaleCount": "11",
  "FemalePCT": "45.83",
  "MaleCount": "13",
  "MalePCT": "54.17",
  "AmericanIndianCount": "0",
  "AmericanIndianPCT": "0.00",
  "AsianCount": "0",
  "AsianPCT": "0.00",
  "BlackAfricanAmericanCount": "21",
  "BlackAfricanAmericanPCT": "87.50",
  "HispanicCount": "3",
  "HispanicPCT": "12.50",
  "MultiRaceCount": "0",
  "MultiRacePCT": "0.00",
  "PacificIslanderCount": "0",
  "PacificIslanderPCT": "0.00",
  "WhiteCount": "0",
  "WhitePCT": "0.00",
  "CEPEconomicallyDisadvantagedRate": ""
 },
 {
  "SchoolYear": "2021-2022",
  "Sector": "District",
  "SubSector": "District",
  "ULCSCode": "4560",
  "SchoolName": "William D. Kelley School",
  "LearningNetwork": "Network 11",
  "GradeLevel": "05",
  "StudentEnrollment": "19",
  "ELCount": "0",
  "ELPCT": "0.00",
  "NotELCount": "19",
  "NotELPCT": "100.00",
  "IEPCount": "2",
  "IEPPCT": "10.53",
  "NotIEPCount": "17",
  "NotIEPPCT": "89.47",
  "FemaleCount": "13",
  "FemalePCT": "68.42",
  "MaleCount": "6",
  "MalePCT": "31.58",
  "AmericanIndianCount": "0",
  "AmericanIndianPCT": "0.00",
  "AsianCount": "0",
  "AsianPCT": "0.00",
  "BlackAfricanAmericanCount": "19",
  "BlackAfricanAmericanPCT": "100.00",
  "HispanicCount": "0",
  "HispanicPCT": "0.00",
  "MultiRaceCount": "0",
  "MultiRacePCT": "0.00",
  "PacificIslanderCount": "0",
  "PacificIslanderPCT": "0.00",
  "WhiteCount": "0",
  "WhitePCT": "0.00",
  "CEPEconomicallyDisadvantagedRate": ""
 },
 {
  "SchoolYear": "2021-2022",
  "Sector": "District",
  "SubSector": "District",
  "ULCSCode": "4560",
  "SchoolName": "William D. Kelley School",
  "LearningNetwork": "Network 11",
  "GradeLevel": "06",
  "StudentEnrollment": "34",
  "ELCount": "0",
  "ELPCT": "0.00",
  "NotELCount": "34",
  "NotELPCT": "100.00",
  "IEPCount": "9",
  "IEPPCT": "26.47",
  "NotIEPCount": "25",
  "NotIEPPCT": "73.53",
  "FemaleCount": "15",
  "FemalePCT": "44.12",
  "MaleCount": "19",
  "MalePCT": "55.88",
  "AmericanIndianCount": "0",
  "AmericanIndianPCT": "0.00",
  "AsianCount": "0",
  "AsianPCT": "0.00",
  "BlackAfricanAmericanCount": "33",
  "BlackAfricanAmericanPCT": "97.06",
  "HispanicCount": "1",
  "HispanicPCT": "2.94",
  "MultiRaceCount": "0",
  "MultiRacePCT": "0.00",
  "PacificIslanderCount": "0",
  "PacificIslanderPCT": "0.00",
  "WhiteCount": "0",
  "WhitePCT": "0.00",
  "CEPEconomicallyDisadvantagedRate": ""
 },
 {
  "SchoolYear": "2021-2022",
  "Sector": "District",
  "SubSector": "District",
  "ULCSCode": "4560",
  "SchoolName": "William D. Kelley School",
  "LearningNetwork": "Network 11",
  "GradeLevel": "07",
  "StudentEnrollment": "27",
  "ELCount": "0",
  "ELPCT": "0.00",
  "NotELCount": "27",
  "NotELPCT": "100.00",
  "IEPCount": "5",
  "IEPPCT": "18.52",
  "NotIEPCount": "22",
  "NotIEPPCT": "81.48",
  "FemaleCount": "13",
  "FemalePCT": "48.15",
  "MaleCount": "14",
  "MalePCT": "51.85",
  "AmericanIndianCount": "0",
  "AmericanIndianPCT": "0.00",
  "AsianCount": "0",
  "AsianPCT": "0.00",
  "BlackAfricanAmericanCount": "27",
  "BlackAfricanAmericanPCT": "100.00",
  "HispanicCount": "0",
  "HispanicPCT": "0.00",
  "MultiRaceCount": "0",
  "MultiRacePCT": "0.00",
  "PacificIslanderCount": "0",
  "PacificIslanderPCT": "0.00",
  "WhiteCount": "0",
  "WhitePCT": "0.00",
  "CEPEconomicallyDisadvantagedRate": ""
 },
 {
  "SchoolYear": "2021-2022",
  "Sector": "District",
  "SubSector": "District",
  "ULCSCode": "4560",
  "SchoolName": "William D. Kelley School",
  "LearningNetwork": "Network 11",
  "GradeLevel": "08",
  "StudentEnrollment": "20",
  "ELCount": "0",
  "ELPCT": "0.00",
  "NotELCount": "20",
  "NotELPCT": "100.00",
  "IEPCount": "1",
  "IEPPCT": "5.00",
  "NotIEPCount": "19",
  "NotIEPPCT": "95.00",
  "FemaleCount": "11",
  "FemalePCT": "55.00",
  "MaleCount": "9",
  "MalePCT": "45.00",
  "AmericanIndianCount": "0",
  "AmericanIndianPCT": "0.00",
  "AsianCount": "0",
  "AsianPCT": "0.00",
  "BlackAfricanAmericanCount": "19",
  "BlackAfricanAmericanPCT": "95.00",
  "HispanicCount": "1",
  "HispanicPCT": "5.00",
  "MultiRaceCount": "0",
  "MultiRacePCT": "0.00",
  "PacificIslanderCount": "0",
  "PacificIslanderPCT": "0.00",
  "WhiteCount": "0",
  "WhitePCT": "0.00",
  "CEPEconomicallyDisadvantagedRate": ""
 },
 {
  "SchoolYear": "2021-2022",
  "Sector": "District",
  "SubSector": "District",
  "ULCSCode": "4560",
  "SchoolName": "William D. Kelley School",
  "LearningNetwork": "Network 11",
  "GradeLevel": "All Grades",
  "StudentEnrollment": "241",
  "ELCount": "0",
  "ELPCT": "0.00",
  "NotELCount": "241",
  "NotELPCT": "100.00",
  "IEPCount": "35",
  "IEPPCT": "14.52",
  "NotIEPCount": "206",
  "NotIEPPCT": "85.48",
  "FemaleCount": "112",
  "FemalePCT": "46.47",
  "MaleCount": "129",
  "MalePCT": "53.53",
  "AmericanIndianCount": "1",
  "AmericanIndianPCT": "0.41",
  "AsianCount": "0",
  "AsianPCT": "0.00",
  "BlackAfricanAmericanCount": "229",
  "BlackAfricanAmericanPCT": "95.02",
  "HispanicCount": "11",
  "HispanicPCT": "4.56",
  "MultiRaceCount": "0",
  "MultiRacePCT": "0.00",
  "PacificIslanderCount": "0",
  "PacificIslanderPCT": "0.00",
  "WhiteCount": "0",
  "WhitePCT": "0.00",
  "CEPEconomicallyDisadvantagedRate": "100.00"
 }
]