[
 {
  "SchoolYear": "2021-2022",
  "Sector": "District",
  "SubSector": "District",
  "ULCSCode": "8400",
  "SchoolName": "Anne Frank School",
  "LearningNetwork": "Network 8",
  "GradeLevel": "00",
  "StudentEnrollment": "187",
  "ELCount": "49",
  "ELPCT": "26.20",
  "NotELCount": "138",
  "NotELPCT": "73.80",
  "IEPCount": "1",
  "IEPPCT": "0.53",
  "NotIEPCount": "186",
  "NotIEPPCT": "99.47",
  "FemaleCount": "94",
  "FemalePCT": "50.27",
  "MaleCount": "93",
  "MalePCT": "49.73",
  "AmericanIndianCount": "0",
  "AmericanIndianPCT": "0.00",
  "AsianCount": "65",
  "AsianPCT": "34.76",
  "BlackAfricanAmericanCount": "32",
  "BlackAfricanAmericanPCT": "17.11",
  "HispanicCount": "17",
  "HispanicPCT": "9.09",
  "MultiRaceCount": "12",
  "MultiRacePCT": "6.42",
  "PacificIslanderCount": "0",
  "PacificIslanderPCT": "0.00",
  "WhiteCount": "61",
  "WhitePCT": "32.62",
  "CEPEconomicallyDisadvantagedRate": ""
 },
 {
  "SchoolYear": "2021-2022",
  "Sector": "District",
  "SubSector": "District",
  "ULCSCode": "8400",
  "SchoolName": "Anne Frank School",
  "LearningNetwork": "Network 8",
  "GradeLevel": "01",
  "StudentEnrollment": "223",
  "ELCount": "87",
  "ELPCT": "39.01",
  "NotELCount": "136",
  "NotELPCT": "60.99",
  "IEPCount": "13",
  "IEPPCT": "5.83",
  "NotIEPCount": "210",
  "NotIEPPCT": "94.17",
  "FemaleCount": "115",
  "FemalePCT": "51.57",
  "MaleCount": "108",
  "MalePCT": "48.43",
  "AmericanIndianCount": "0",
  "AmericanIndianPCT": "0.00",
  "AsianCount": "60",
  "AsianPCT": "26.91",
  "BlackAfricanAmericanCount": "43",
  "BlackAfricanAmericanPCT": "19.28",
  "HispanicCount": "30",
  "HispanicPCT": "13.45",
  "MultiRaceCount": "5",
  "MultiRacePCT": "2.24",
  "PacificIslanderCount": "0",
  "PacificIslanderPCT": "0.00",
  "WhiteCount": "85",
  "WhitePCT": "38.12",
  "CEPEconomicallyDisadvantagedRate": ""
 },
 {
  "SchoolYear": "2021-2022",
  "Sector": "District",
  "SubSector": "District",
  "ULCSCode": "8400",
  "SchoolName": "Anne Frank School",
  "LearningNetwork": "Network 8",
  "GradeLevel": "02",
  "StudentEnrollment": "232",
  "ELCount": "77",
  "ELPCT": "33.19",
  "NotELCount": "155",
  "NotELPCT": "66.81",
  "IEPCount": "3",
  "IEPPCT": "1.29",
  "NotIEPCount": "229",
  "NotIEPPCT": "98.71",
  "FemaleCount": "106",
  "FemalePCT": "45.69",
  "MaleCount": "126",
  "MalePCT": "54.31",
  "AmericanIndianCount": "0",
  "AmericanIndianPCT": "0.00",
  "AsianCount": "93",
  "AsianPCT": "40.09",
  "BlackAfricanAmericanCount": "37",
  "BlackAfricanAmericanPCT": "15.95",
  "HispanicCount": "17",
  "HispanicPCT": "7.33",
  "MultiRaceCount": "2",
  "MultiRacePCT": "0.86",
  "PacificIslanderCount": "1",
  "PacificIslanderPCT": "0.43",
  "WhiteCount": "82",
  "WhitePCT": "35.34",
  "CEPEconomicallyDisadvantagedRate": ""
 },
 {
  "SchoolYear": "2021-2022",
  "Sector": "District",
  "SubSector": "District",
  "ULCSCode": "8400",
  "SchoolName": "Anne Frank School",
  "LearningNetwork": "Network 8",
  "GradeLevel": "03",
  "StudentEnrollment": "194",
  "ELCount": "61",
  "ELPCT": "31.44",
  "NotELCount": "133",
  "NotELPCT": "68.56",
  "IEPCount": "15",
  "IEPPCT": "7.73",
  "NotIEPCount": "179",
  "NotIEPPCT": "92.27",
  "FemaleCount": "85",
  "FemalePCT": "43.81",
  "MaleCount": "109",
  "MalePCT": "56.19",
  "AmericanIndianCount": "0",
  "AmericanIndianPCT": "0.00",
  "AsianCount": "76",
  "AsianPCT": "39.18",
  "BlackAfricanAmericanCount": "21",
  "BlackAfricanAmericanPCT": "10.82",
  "HispanicCount": "25",
  "HispanicPCT": "12.89",
  "MultiRaceCount": "4",
  "MultiRacePCT": "2.06",
  "PacificIslanderCount": "0",
  "PacificIslanderPCT": "0.00",
  "WhiteCount": "68",
  "WhitePCT": "35.05",
  "CEPEconomicallyDisadvantagedRate": ""
 },
 {
  "SchoolYear": "2021-2022",
  "Sector": "District",
  "SubSector": "District",
  "ULCSCode": "8400",
  "SchoolName": "Anne Frank School",
  "LearningNetwork": "Network 8",
  "GradeLevel": "04",
  "StudentEnrollment": "211",
  "ELCount": "53",
  "ELPCT": "25.12",
  "NotELCount": "158",
  "NotELPCT": "74.88",
  "IEPCount": "12",
  "IEPPCT": "5.69",
  "NotIEPCount": "199",
  "NotIEPPCT": "94.31",
  "FemaleCount": "93",
  "FemalePCT": "44.08",
  "MaleCount": "118",
  "MalePCT": "55.92",
  "AmericanIndianCount": "0",
  "AmericanIndianPCT": "0.00",
  "AsianCount": "81",
  "AsianPCT": "38.39",
  "BlackAfricanAmericanCount": "20",
  "BlackAfricanAmericanPCT": "9.48",
  "HispanicCount": "18",
  "HispanicPCT": "8.53",
  "MultiRaceCount": "4",
  "MultiRacePCT": "1.90",
  "PacificIslanderCount": "0",
  "PacificIslanderPCT": "0.00",
  "WhiteCount": "88",
  "WhitePCT": "41.71",
  "CEPEconomicallyDisadvantagedRate": ""
 },
 {
  "SchoolYear": "2021-2022",
  "Sector": "District",
  "SubSector": "District",
  "ULCSCode": "8400",
  "SchoolName": "Anne Frank School",
  "LearningNetwork": "Network 8",
  "GradeLevel": "05",
  "StudentEnrollment": "216",
  "ELCount": "55",
  "ELPCT": "25.46",
  "NotELCount": "161",
  "NotELPCT": "74.54",
  "IEPCount": "17",
  "IEPPCT": "7.87",
  "NotIEPCount": "199",
  "NotIEPPCT": "92.13",
  "FemaleCount": "109",
  "FemalePCT": "50.46",
  "MaleCount": "107",
  "MalePCT": "49.54",
  "AmericanIndianCount": "2",
  "AmericanIndianPCT": "0.93",
  "AsianCount": "63",
  "AsianPCT": "29.17",
  "BlackAfricanAmericanCount": "32",
  "BlackAfricanAmericanPCT": "14.81",
  "HispanicCount": "13",
  "HispanicPCT": "6.02",
  "MultiRaceCount": "11",
  "MultiRacePCT": "5.09",
  "PacificIslanderCount": "0",
  "PacificIslanderPCT": "0.00",
  "WhiteCount": "95",
  "WhitePCT": "43.98",
  "CEPEconomicallyDisadvantagedRate": ""
 },
 {
  "SchoolYear": "2021-2022",
  "Sector": "District",
  "SubSector": "District",
  "ULCSCode": "8400",
  "SchoolName": "Anne Frank School",
  "LearningNetwork": "Network 8",
  "GradeLevel": "All Grades",
  "StudentEnrollment": "1263",
  "ELCount": "382",
  "ELPCT": "30.25",
  "NotELCount": "881",
  "NotELPCT": "69.75",
  "IEPCount": "61",
  "IEPPCT": "4.83",
  "NotIEPCount": "1202",
  "NotIEPPCT": "95.17",
  "FemaleCount": "602",
  "FemalePCT": "47.66",
  "MaleCount": "661",
  "MalePCT": "52.34",
  "AmericanIndianCount": "2",
  "AmericanIndianPCT": "0.16",
  "AsianCount": "438",
  "AsianPCT": "34.68",
  "BlackAfricanAmericanCount": "185",
  "BlackAfricanAmericanPCT": "14.65",
  "HispanicCount": "120",
  "HispanicPCT": "9.50",
  "MultiRaceCount": "38",
  "MultiRacePCT": "3.01",
  "PacificIslanderCount": "1",
  "PacificIslanderPCT": "0.08",
  "WhiteCount": "479",
  "WhitePCT": "37.93",
  "CEPEconomicallyDisadvantagedRate": "96.28"
 }
]